qcbc/__init__.py
qcbc/main.py
qcbc/qcbc_ambiguous.py
qcbc/qcbc_content.py
qcbc/qcbc_homopolymer.py
qcbc/qcbc_pdist.py
qcbc/qcbc_volume.py
qcbc/utils.py
qcbc-0.0.2.dist-info/LICENSE
qcbc-0.0.2.dist-info/METADATA
qcbc-0.0.2.dist-info/WHEEL
qcbc-0.0.2.dist-info/entry_points.txt
qcbc-0.0.2.dist-info/top_level.txt
qcbc-0.0.2.dist-info/RECORD
