Metadata-Version: 2.1
Name: qcbc
Version: 0.0.2
Summary: Quality Control of BarCodes.
Author-email: "A. Sina Booeshaghi" <alisina@caltech.edu>
License: MIT License        
Project-URL: Homepage, https://github.com/pachterlab/qcbc
Project-URL: Bug Tracker, https://github.com/pachterlab/qcbc/issues
Classifier: Environment :: Console
Classifier: Intended Audience :: Science/Research
Classifier: License :: OSI Approved :: MIT License
Classifier: Operating System :: OS Independent
Classifier: Programming Language :: Python :: 3.6
Classifier: Programming Language :: Python :: 3.7
Classifier: Programming Language :: Python :: 3.8
Classifier: Programming Language :: Python :: 3.9
Classifier: Programming Language :: Python :: 3.10
Classifier: Topic :: Scientific/Engineering :: Bio-Informatics
Classifier: Topic :: Utilities
Requires-Python: >=3.7
License-File: LICENSE
Requires-Dist: numpy (==1.21.6)
Requires-Dist: scipy (==1.7.3)
